.gitignore
.swagger-codegen-ignore
.travis.yml
README.md
__init__.py
api_usage.ipynb
api_usage.py
git_push.sh
requirements.txt
setup.cfg
setup.py
test-requirements.txt
test.ps1
tox.ini
conquest/__init__.py
conquest/api_client.py
conquest/configuration.py
conquest/rest.py
conquest.egg-info/PKG-INFO
conquest.egg-info/SOURCES.txt
conquest.egg-info/dependency_links.txt
conquest.egg-info/requires.txt
conquest.egg-info/top_level.txt
conquest/api/__init__.py
conquest/api/action_service_api.py
conquest/api/asset_inspection_service_api.py
conquest/api/asset_service_api.py
conquest/api/csv_import_service_api.py
conquest/api/defect_service_api.py
conquest/api/document_service_api.py
conquest/api/geo_service_api.py
conquest/api/jobs_service_api.py
conquest/api/knowledge_base_service_api.py
conquest/api/request_service_api.py
conquest/api/system_service_api.py
conquest/api/view_service_api.py
conquest/models/__init__.py
conquest/models/conquest_api_account_id.py
conquest/models/conquest_api_account_permissions.py
conquest/models/conquest_api_account_type.py
conquest/models/conquest_api_action_assignment.py
conquest/models/conquest_api_action_completion_details.py
conquest/models/conquest_api_action_completion_options.py
conquest/models/conquest_api_action_entity.py
conquest/models/conquest_api_action_record.py
conquest/models/conquest_api_action_record_change_set.py
conquest/models/conquest_api_action_schedule.py
conquest/models/conquest_api_action_schedule_list.py
conquest/models/conquest_api_action_schedule_type.py
conquest/models/conquest_api_action_task.py
conquest/models/conquest_api_action_tasks_list.py
conquest/models/conquest_api_action_type.py
conquest/models/conquest_api_add_diary_result.py
conquest/models/conquest_api_add_document_command.py
conquest/models/conquest_api_add_document_result.py
conquest/models/conquest_api_add_document_results.py
conquest/models/conquest_api_add_geo_update_command.py
conquest/models/conquest_api_add_new_csv_import_command.py
conquest/models/conquest_api_add_new_geo_package_import_command.py
conquest/models/conquest_api_any_value.py
